{
  "schemaVersion": 5,
  "parserA": "epubts-node",
  "parserB": "epubts-browser",
  "metadata": {
    "title": {
      "status": "agree",
      "a": "The Blood Mirror",
      "b": "The Blood Mirror"
    },
    "creator": {
      "status": "agree",
      "a": "Brent Weeks",
      "b": "Brent Weeks"
    },
    "date": {
      "status": "agree",
      "a": "2016-10-25T00:00:00+00:00",
      "b": "2016-10-25T00:00:00+00:00"
    }
  },
  "spine": {
    "status": "agree",
    "countA": 95,
    "countB": 95,
    "onlyInA": [],
    "onlyInB": []
  },
  "manifest": {
    "status": "agree",
    "countA": 111,
    "countB": 111,
    "onlyInA": [],
    "onlyInB": []
  },
  "spineHashes": {
    "status": "agree",
    "matchCount": 95,
    "mismatchCount": 0
  }
}
