{
  "schemaVersion": 2,
  "parserA": "epubts-node",
  "parserB": "epubts-browser",
  "metadata": {
    "title": {
      "status": "agree",
      "a": "And Every Morning the Way Home Gets Longer and Longer",
      "b": "And Every Morning the Way Home Gets Longer and Longer"
    },
    "creator": {
      "status": "agree",
      "a": "Fredrik Backman",
      "b": "Fredrik Backman"
    },
    "date": {
      "status": "both-null",
      "a": null,
      "b": null
    }
  },
  "spine": {
    "status": "agree",
    "countA": 20,
    "countB": 20,
    "onlyInA": [],
    "onlyInB": []
  }
}
