{
  "schemaVersion": 5,
  "parserA": "epubts-node",
  "parserB": "epubts-browser",
  "metadata": {
    "title": {
      "status": "agree",
      "a": "The Biggest Ideas in the Universe 1",
      "b": "The Biggest Ideas in the Universe 1"
    },
    "creator": {
      "status": "agree",
      "a": "Sean Carroll",
      "b": "Sean Carroll"
    },
    "date": {
      "status": "both-null",
      "a": null,
      "b": null
    }
  },
  "spine": {
    "status": "agree",
    "countA": 20,
    "countB": 20,
    "onlyInA": [],
    "onlyInB": []
  },
  "manifest": {
    "status": "agree",
    "countA": 391,
    "countB": 391,
    "onlyInA": [],
    "onlyInB": []
  },
  "spineHashes": {
    "status": "agree",
    "matchCount": 20,
    "mismatchCount": 0
  }
}
