{
  "schemaVersion": 4,
  "parserA": "epubts-node",
  "parserB": "epubts-browser",
  "metadata": {
    "title": {
      "status": "agree",
      "a": "Trouble on Paradise",
      "b": "Trouble on Paradise"
    },
    "creator": {
      "status": "agree",
      "a": "Craig Alanson",
      "b": "Craig Alanson"
    },
    "date": {
      "status": "agree",
      "a": "2017-03-21T22:00:00+00:00",
      "b": "2017-03-21T22:00:00+00:00"
    }
  },
  "spine": {
    "status": "agree",
    "countA": 15,
    "countB": 15,
    "onlyInA": [],
    "onlyInB": []
  },
  "manifest": {
    "status": "agree",
    "countA": 19,
    "countB": 19,
    "onlyInA": [],
    "onlyInB": []
  },
  "spineHashes": {
    "status": "agree",
    "matchCount": 15,
    "mismatchCount": 0
  }
}
