{
  "schemaVersion": 4,
  "meta": {
    "parser": "epubts-browser",
    "parserVersion": "0.3",
    "openStatus": "opened"
  },
  "content": {
    "metadata": {
      "title": "The Fifth Elephant",
      "creator": "Terry Pratchett",
      "date": "2001-04-02T03:00:00+00:00"
    },
    "spine": [
      {
        "href": "titlepage.xhtml",
        "linear": true
      },
      {
        "href": "The_Fifth_Elephant_split_000.html",
        "linear": true
      },
      {
        "href": "The_Fifth_Elephant_split_001.html",
        "linear": true
      },
      {
        "href": "The_Fifth_Elephant_split_002.html",
        "linear": true
      },
      {
        "href": "The_Fifth_Elephant_split_003.html",
        "linear": true
      },
      {
        "href": "The_Fifth_Elephant_split_004.html",
        "linear": true
      },
      {
        "href": "The_Fifth_Elephant_split_005.html",
        "linear": true
      },
      {
        "href": "The_Fifth_Elephant_split_006.html",
        "linear": true
      },
      {
        "href": "The_Fifth_Elephant_split_007.html",
        "linear": true
      },
      {
        "href": "The_Fifth_Elephant_split_008.html",
        "linear": true
      },
      {
        "href": "The_Fifth_Elephant_split_009.html",
        "linear": true
      },
      {
        "href": "The_Fifth_Elephant_split_010.html",
        "linear": true
      },
      {
        "href": "The_Fifth_Elephant_split_011.html",
        "linear": true
      },
      {
        "href": "The_Fifth_Elephant_split_012.html",
        "linear": true
      },
      {
        "href": "The_Fifth_Elephant_split_013.html",
        "linear": true
      }
    ],
    "manifest": [
      {
        "id": "cover",
        "href": "cover.jpeg",
        "mediaType": "image/jpeg"
      },
      {
        "id": "css",
        "href": "stylesheet.css",
        "mediaType": "text/css"
      },
      {
        "id": "id11",
        "href": "The_Fifth_Elephant_split_013.html",
        "mediaType": "application/xhtml+xml"
      },
      {
        "id": "id110",
        "href": "The_Fifth_Elephant_split_004.html",
        "mediaType": "application/xhtml+xml"
      },
      {
        "id": "id111",
        "href": "The_Fifth_Elephant_split_003.html",
        "mediaType": "application/xhtml+xml"
      },
      {
        "id": "id112",
        "href": "The_Fifth_Elephant_split_002.html",
        "mediaType": "application/xhtml+xml"
      },
      {
        "id": "id113",
        "href": "The_Fifth_Elephant_split_001.html",
        "mediaType": "application/xhtml+xml"
      },
      {
        "id": "id114",
        "href": "The_Fifth_Elephant_split_000.html",
        "mediaType": "application/xhtml+xml"
      },
      {
        "id": "id12",
        "href": "The_Fifth_Elephant_split_012.html",
        "mediaType": "application/xhtml+xml"
      },
      {
        "id": "id13",
        "href": "The_Fifth_Elephant_split_011.html",
        "mediaType": "application/xhtml+xml"
      },
      {
        "id": "id14",
        "href": "The_Fifth_Elephant_split_010.html",
        "mediaType": "application/xhtml+xml"
      },
      {
        "id": "id15",
        "href": "The_Fifth_Elephant_split_009.html",
        "mediaType": "application/xhtml+xml"
      },
      {
        "id": "id16",
        "href": "The_Fifth_Elephant_split_008.html",
        "mediaType": "application/xhtml+xml"
      },
      {
        "id": "id17",
        "href": "The_Fifth_Elephant_split_007.html",
        "mediaType": "application/xhtml+xml"
      },
      {
        "id": "id18",
        "href": "The_Fifth_Elephant_split_006.html",
        "mediaType": "application/xhtml+xml"
      },
      {
        "id": "id19",
        "href": "The_Fifth_Elephant_split_005.html",
        "mediaType": "application/xhtml+xml"
      },
      {
        "id": "id3",
        "href": "images/00001.jpg",
        "mediaType": "image/jpeg"
      },
      {
        "id": "id4",
        "href": "images/00002.jpg",
        "mediaType": "image/jpeg"
      },
      {
        "id": "ncx",
        "href": "toc.ncx",
        "mediaType": "application/x-dtbncx+xml"
      },
      {
        "id": "titlepage",
        "href": "titlepage.xhtml",
        "mediaType": "application/xhtml+xml"
      }
    ],
    "spineHashes": [
      {
        "href": "titlepage.xhtml",
        "sha256": "17458bbfa62b6b1bcf31e880b43c7d61d1476be9fcd2e29f7d44f01feadcd8ca"
      },
      {
        "href": "The_Fifth_Elephant_split_000.html",
        "sha256": "4b4eb855c4cc431c431da0af0650bf62ba046093ebc3dbb79c56c3ecb0fe9cb4"
      },
      {
        "href": "The_Fifth_Elephant_split_001.html",
        "sha256": "e214f5c47d0f6f5967c0cfab410bf2219d9f601ef00ef929f90874cc7751e1ce"
      },
      {
        "href": "The_Fifth_Elephant_split_002.html",
        "sha256": "2b39d4876ab4bbb2c548a66c3a6a50a14d9f27556675bdc2704b76e8a3a00d5b"
      },
      {
        "href": "The_Fifth_Elephant_split_003.html",
        "sha256": "7cbc94ad1ab5a3d5233ff01f5a1a459ed87ef172399b14fea199cb9b4e57292a"
      },
      {
        "href": "The_Fifth_Elephant_split_004.html",
        "sha256": "334b70bae0a8e2198a1e9f3f097c3ef38a9113aa4c8c029dd17fc386b5e7558d"
      },
      {
        "href": "The_Fifth_Elephant_split_005.html",
        "sha256": "cea1a140ac986af8ac550af78c34da7af0a42e0dca704a60b4e5cea34fc848e9"
      },
      {
        "href": "The_Fifth_Elephant_split_006.html",
        "sha256": "4d4ba4c56cca9830e6bf79e085988e8bc40020af623904dbe4db8c4942b7c9fb"
      },
      {
        "href": "The_Fifth_Elephant_split_007.html",
        "sha256": "5ee36b460049ae539b74744d46ec8e3d762b82819572c88e9834fbfa1a701301"
      },
      {
        "href": "The_Fifth_Elephant_split_008.html",
        "sha256": "468b47d5f1ef40192b712f83a7763aacb4aaf7fd7f073cf6405ba191839da307"
      },
      {
        "href": "The_Fifth_Elephant_split_009.html",
        "sha256": "67fafbc735aececa74bf4e0c7dffeabfc6d81faaec4c6a9be26291f7d2103587"
      },
      {
        "href": "The_Fifth_Elephant_split_010.html",
        "sha256": "51c435ea240ca54cfb6de611ecbbddf400d150c1484d7224a0780c2bba5ec794"
      },
      {
        "href": "The_Fifth_Elephant_split_011.html",
        "sha256": "9548928f98e635d0fc9a9d5c6ed751e9352a06e9beda2e24b820fb820e4abedf"
      },
      {
        "href": "The_Fifth_Elephant_split_012.html",
        "sha256": "157db5f9fe2a2af0969d0f7b31ff5b9b6ba12c1ad03b3de820b67709c5ffaded"
      },
      {
        "href": "The_Fifth_Elephant_split_013.html",
        "sha256": "3dfc601ac3013b1a74a791c5348873147cb4ab8c41b8214da60c042dcdfa732c"
      }
    ]
  }
}
