{
  "schemaVersion": 5,
  "book": {
    "root": "drop",
    "relativePath": "Tony Fadell - Build.epub",
    "size": 9944039,
    "sha256": "1ceb22cee3db13fdc8cfbd5f432414bbffcbe3e135b9d231b4da15eb2cdd645a",
    "shortSha": "1ceb22c"
  },
  "parsers": {
    "epubts-browser": {
      "status": "transported",
      "byteLength": 9944039,
      "sha256": "1ceb22cee3db13fdc8cfbd5f432414bbffcbe3e135b9d231b4da15eb2cdd645a",
      "epubtsVersion": "0.3",
      "open": {
        "status": "opened",
        "version": {
          "status": "skipped"
        }
      },
      "diagnostics": []
    },
    "epubts-node": {
      "status": "node-opened",
      "version": {
        "status": "skipped"
      },
      "engine": "linkedom"
    },
    "storyteller-node": {
      "status": "storyteller-opened",
      "version": {
        "status": "exposed",
        "value": "3.0"
      }
    }
  },
  "comparison": {
    "status": "not-implemented"
  }
}
