{
  "schemaVersion": 3,
  "book": {
    "root": "drop",
    "relativePath": "Ali Abdaal - Feel-Good Productivity.epub",
    "size": 748129,
    "sha256": "912a71359c99abe6191e2870c3cb87e44e3a70186a2a8105465bbc6834c5f3b9",
    "shortSha": "912a713"
  },
  "parsers": {
    "epubts-browser": {
      "status": "transported",
      "byteLength": 748129,
      "sha256": "912a71359c99abe6191e2870c3cb87e44e3a70186a2a8105465bbc6834c5f3b9",
      "epubtsVersion": "0.3",
      "open": {
        "status": "opened",
        "version": {
          "status": "skipped"
        }
      },
      "diagnostics": []
    },
    "epubts-node": {
      "status": "node-opened",
      "version": {
        "status": "skipped"
      }
    },
    "storyteller-node": {
      "status": "not-implemented"
    }
  },
  "comparison": {
    "status": "not-implemented"
  }
}
