{
  "schemaVersion": 5,
  "book": {
    "root": "drop",
    "relativePath": "Tom Holland - Rubicon.epub",
    "size": 1974671,
    "sha256": "c9b99e1dd2944985c923a4f7c3b14dc4325c462585a8e854ca5161867b94ab67",
    "shortSha": "c9b99e1"
  },
  "parsers": {
    "epubts-browser": {
      "status": "transported",
      "byteLength": 1974671,
      "sha256": "c9b99e1dd2944985c923a4f7c3b14dc4325c462585a8e854ca5161867b94ab67",
      "epubtsVersion": "0.3",
      "open": {
        "status": "opened",
        "version": {
          "status": "skipped"
        }
      },
      "diagnostics": []
    },
    "epubts-node": {
      "status": "node-opened",
      "version": {
        "status": "skipped"
      },
      "engine": "linkedom"
    },
    "storyteller-node": {
      "status": "storyteller-open-failed",
      "stage": "storyteller-open",
      "category": "Error",
      "message": "This is not a valid EPUB 3 publication. This library only supports EPUB 3, not EPUB 2. Use Epub.upgrade(path) to convert."
    }
  },
  "comparison": {
    "status": "not-implemented"
  }
}
